Metadata-Version: 2.4
Name: Cirilla
Version: 0.2.0
Summary: Crilla is a simple way to introduce optimized single-GPU training into your project
Requires-Python: >=3.10
Requires-Dist: aiofiles>=24.1.0
Requires-Dist: attn-gym>=0.0.4
Requires-Dist: bitsandbytes>=0.46.1
Requires-Dist: datasets>=4.0.0
Requires-Dist: ema-pytorch>=0.7.7
Requires-Dist: fandom-py>=0.2.1
Requires-Dist: fuzzywuzzy>=0.18.0
Requires-Dist: huggingface-hub>=0.33.4
Requires-Dist: kernels>=0.8.0
Requires-Dist: ollama>=0.5.3
Requires-Dist: openai>=1.90.0
Requires-Dist: polars>=1.35.1
Requires-Dist: progress-table>=3.1.2
Requires-Dist: pydantic>=2.11.7
Requires-Dist: pytest>=7.4.4
Requires-Dist: python-levenshtein>=0.27.1
Requires-Dist: reasoning-gym>=0.1.23
Requires-Dist: rich>=14.1.0
Requires-Dist: sentencepiece>=0.2.0
Requires-Dist: span-marker>=1.7.0
Requires-Dist: tokenizers>=0.21.2
Requires-Dist: torch>=2.7.0
Requires-Dist: torchao==0.13.0
Requires-Dist: torchvision>=0.22.0
Requires-Dist: transformers>=4.53.2
Requires-Dist: vllm>=0.9.2
Provides-Extra: megablocks
Requires-Dist: megablocks[all]>=0.10.0; extra == "megablocks"
Provides-Extra: mamba
Requires-Dist: mamba-ssm[causal-conv1d]>=2.2.6.post3; extra == "mamba"
